{
  "$schema": "https://developer.microsoft.com/json-schemas/fabric/item/report/definition/visualContainer/2.0.0/schema.json",
  "name": "03_Champion_Role_Meta_kpi_4",
  "position": {
    "x": 489,
    "y": 92,
    "z": 1038,
    "height": 74,
    "width": 147,
    "tabOrder": 1038
  },
  "visual": {
    "visualType": "cardVisual",
    "drillFilterOtherVisuals": true,
    "query": {
      "queryState": {
        "Data": {
          "projections": [
            {
              "field": {
                "Measure": {
                  "Expression": {
                    "SourceRef": {
                      "Entity": "dim_date"
                    }
                  },
                  "Property": "Champion Pick Rate"
                }
              },
              "queryRef": "dim_date.Champion Pick Rate",
              "nativeQueryRef": "Pick Rate"
            }
          ]
        }
      }
    },
    "visualContainerObjects": {
      "title": [
        {
          "properties": {
            "show": {
              "expr": {
                "Literal": {
                  "Value": "true"
                }
              }
            },
            "text": {
              "expr": {
                "Literal": {
                  "Value": "'Pick Rate'"
                }
              }
            }
          }
        }
      ],
      "visualHeader": [
        {
          "properties": {
            "show": {
              "expr": {
                "Literal": {
                  "Value": "false"
                }
              }
            }
          }
        }
      ]
    }
  }
}